{
    "utilityHed": "[data-testid='UtilityLedeHedText']",
    "utilityDek": "[data-testid='UtilityLedeDekText']",
    "newsletterImage": "[class *='NewsletterCardWrapper']>[class *='responsive-asset']",
    "newsletterSectionhed": "[class *='NewsletterSectionHed']",
    "newsletterCard": "[class *='NewsletterCardWrapper']",
    "newsletterCardCheckbox": "[class *='NewsletterCardNativeCheckbox']",
    "newsletterCatogoryWrapper": "[class *='NewsletterCategoryWrapper']",
    "signUpCheckbox": "[class *='NewsletterCardWrapper']>[class *='NewsletterCardStyledCheckbox']",
    "subscribeCheckbox": "[class *='NewsletterCardWrapper']>[class *='NewsletterCardNativeCheckbox']",
    "newsletterCardHed": "[class *='NewsletterCardHed']",
    "newsletterCardDek": "[class *='NewsletterCardDek']",
    "newsletterCardFrequencyBadge": "[class *='NewsletterCardPreviewFrequencyBadge']",
    "newsletterPreview": "[class *='NewsletterCardPreviewLink']",
    "subscribeBanner": "[data-testid='message-banner']",
    "accountsDropdown": ".account-links__navigation [data-testid='navigation__list'] > li >a",
    "navigationDropdown": "[class*='NavigationDropdownListWrapper'] > li > a",
    "discoveryAccountHed": "[class*='DiscoverySelectionControlHed']",
    "accountHed": "[class*='AccountNewsletterToggleHed']",
    "discoveryAccountDek": "[class*='DiscoverySelectionControlDek']",
    "accountDek": "[class*='AccountNewsletterToggleDek']",
    "accountNLCheckbox": "[class*='DiscoverySelectionControlNativeCheckbox']",
    "preferenceSubmitBtn": "[class*='NewsletterManageAuthenticatedSubmitButton'] > span",
    "accountsUnsubscribeBtn": "[class*='AccountNewsletterToggleUnsubscribeButton'] > span",
    "enterEmailButtonCount": "[class *= 'NewsLetterManagePageSubmitModelSignUpBtn'] .button-count",
    "enterEmailButtonLabel": "[class *= 'NewsLetterManagePageSubmitModelSignUpBtn'] .button__label",
    "emailButton": "[class *= 'NewsLetterManagePageSubmitModelSignUpBtn']",
    "signUpModel": "[class *= 'NewsLetterManagePageSubmitModel-']",
    "emailTextBox": "[class *= 'TextFieldInputContainer']",
    "signUpButton": "[class*='TextFieldButton']",
    "signUpButtonCount": "[class*='TextFieldButton'] .button-count",
    "signUpButtonLabel": "[class*='TextFieldButton'] .button__label",
    "disclaimerText": "[class *= 'NewsLetterManagePageDisclaimer']",
    "disclaimerTextHyperLink": "[class *= 'NewsLetterManagePageDisclaimer'] > p > a",
    "signUpErrorMessage": "[class *= 'TextFieldErrorText']",
    "newsletterLeftImage": "[class *= 'NewsLetterLeftPanel']",
    "previewButton": "[class *= 'NewsLetterManagePagePreviewLink']",
    "previewWrapper": "[class *= 'NewsLetterPreviewWrapper']",
    "signupButton": "[class*='button button--primary']",
    "closeSubmitModel": "[class*='NewsLetterManagePageCloseSubmitModel']",
    "closeIcon": "[class*='NewsLetterManagePageSubmitModel']> [class *= 'BaseButton']"
}
